hitcount/__init__.py
hitcount/admin.py
hitcount/apps.py
hitcount/mixins.py
hitcount/signals.py
hitcount/urls.py
hitcount/utils.py
hitcount/views.py
hitcount/conf/__init__.py
hitcount/conf/defaults.py
hitcount/locale/ru/LC_MESSAGES/django.po
hitcount/management/__init__.py
hitcount/management/commands/__init__.py
hitcount/management/commands/hitcount_cleanup.py
hitcount/managers/__init__.py
hitcount/managers/blockers.py
hitcount/managers/hits.py
hitcount/migrations/0001_initial.py
hitcount/migrations/0002_index_ip_and_session.py
hitcount/migrations/0003_auto_20190608_1004.py
hitcount/migrations/0004_auto_20200704_0933.py
hitcount/migrations/0005_auto_20210616_2026.py
hitcount/migrations/__init__.py
hitcount/models/__init__.py
hitcount/models/blockers.py
hitcount/models/hits.py
hitcount/static/hitcount/hitcount-jquery.js
hitcount/static/hitcount/jquery.postcsrf.js
hitcount/templatetags/__init__.py
hitcount/templatetags/hitcount_tags.py
dj_hitcount-2.0.0.dist-info/METADATA
dj_hitcount-2.0.0.dist-info/WHEEL
dj_hitcount-2.0.0.dist-info/licenses/LICENSE
dj_hitcount-2.0.0.dist-info/RECORD
