Metadata-Version: 2.4
Name: dj-hitcount
Version: 2.0.0
Summary: Hit counting application for django
Project-URL: Homepage, https://github.com/abhiabhi94/dj-hitcount
Project-URL: Repository, https://github.com/abhiabhi94/dj-hitcount
Project-URL: Documentation, https://dj-hitcount.readthedocs.io
Author: Abhyudai
License: MIT
License-File: LICENSE
Keywords: django,hit,hitcount,hits,views
Classifier: Environment :: Web Environment
Classifier: Framework :: Django
Classifier: Framework :: Django :: 4.2
Classifier: Framework :: Django :: 5.0
Classifier: Framework :: Django :: 5.1
Classifier: Framework :: Django :: 5.2
Classifier: Intended Audience :: Developers
Classifier: License :: OSI Approved :: MIT License
Classifier: Operating System :: OS Independent
Classifier: Programming Language :: Python
Classifier: Programming Language :: Python :: 3.10
Classifier: Programming Language :: Python :: 3.11
Classifier: Programming Language :: Python :: 3.12
Classifier: Programming Language :: Python :: 3.13
Classifier: Topic :: Internet :: WWW/HTTP
Classifier: Topic :: Internet :: WWW/HTTP :: Dynamic Content
Requires-Python: >=3.10
Requires-Dist: django>=4.2
Provides-Extra: dev
Requires-Dist: coverage; extra == 'dev'
Requires-Dist: pre-commit; extra == 'dev'
Requires-Dist: pytest; extra == 'dev'
Requires-Dist: pytest-django; extra == 'dev'
Requires-Dist: pytest-randomly; extra == 'dev'
Requires-Dist: selenium; extra == 'dev'
Provides-Extra: docs
Requires-Dist: furo; extra == 'docs'
Requires-Dist: sphinx; extra == 'docs'
